smbcrawler/__init__.py
smbcrawler/__main__.py
smbcrawler/app.py
smbcrawler/clickargs.py
smbcrawler/crawl.py
smbcrawler/default_profile.yml
smbcrawler/html.py
smbcrawler/io.py
smbcrawler/log.py
smbcrawler/monkeypatch.py
smbcrawler/profiles.py
smbcrawler/queries.py
smbcrawler/reporter.py
smbcrawler/reporting.py
smbcrawler/shares.py
smbcrawler/sql.py
smbcrawler/version.py
smbcrawler/assets/html_templates/base.html
smbcrawler/assets/html_templates/biome.json
smbcrawler/assets/html_templates/index.html
smbcrawler/assets/html_templates/info.html
smbcrawler/assets/html_templates/paths.html
smbcrawler/assets/html_templates/secrets.html
smbcrawler/assets/html_templates/secrets_cleanup_guide.html
smbcrawler/assets/html_templates/shares.html
smbcrawler/assets/html_templates/sidebar.html
smbcrawler/assets/html_templates/targets.html
smbcrawler/assets/html_templates/tree.html
smbcrawler/assets/static/bootstrap-icons.min.css
smbcrawler/assets/static/bootstrap.bundle.min.js
smbcrawler/assets/static/bootstrap.min.css
smbcrawler/assets/static/common.js
smbcrawler/assets/static/gridjs.production.min.js
smbcrawler/assets/static/mermaid.min.css
smbcrawler/assets/static/secrets_cleanup_guide.js
smbcrawler/assets/static/sql-wasm.min.js
smbcrawler/assets/static/sql-wasm.wasm
smbcrawler/assets/static/tree.css
smbcrawler/assets/static/tree.js
smbcrawler/assets/static/fonts/bootstrap-icons.woff
smbcrawler/assets/static/fonts/bootstrap-icons.woff2
smbcrawler-1.2.0.dist-info/METADATA
smbcrawler-1.2.0.dist-info/WHEEL
smbcrawler-1.2.0.dist-info/entry_points.txt
smbcrawler-1.2.0.dist-info/licenses/LICENSE
smbcrawler-1.2.0.dist-info/RECORD
