Metadata-Version: 2.4
Name: smbcrawler
Version: 1.2.0
Summary: Search SMB shares for interesting files
Project-URL: Homepage, https://github.com/SySS-Research/smbcrawler
Project-URL: Bug Tracker, https://github.com/SySS-Research/smbcrawler/issues
Author-email: Adrian Vollmer <adrian.vollmer@syss.de>
License: MIT License
License-File: LICENSE
Keywords: pentest,reconnaissance,shares,smb
Classifier: Operating System :: POSIX :: Linux
Classifier: Programming Language :: Python
Classifier: Programming Language :: Python :: 3
Classifier: Programming Language :: Python :: 3.8
Classifier: Programming Language :: Python :: 3.9
Classifier: Programming Language :: Python :: 3.10
Classifier: Programming Language :: Python :: 3.11
Requires-Python: >=3.10
Requires-Dist: click
Requires-Dist: impacket>=0.9.20
Requires-Dist: lxml
Requires-Dist: peewee
Requires-Dist: python-libnmap
Requires-Dist: python-magic
Requires-Dist: pyyaml
Requires-Dist: xdg-base-dirs
Requires-Dist: zundler>=0.2.1
Provides-Extra: binary-conversion
Requires-Dist: markitdown; extra == 'binary-conversion'
